gcmd/__init__.py
gcmd/__main__.py
gcmd/auth.py
gcmd/cli.py
gcmd/client.py
gcmd/comments.py
gcmd/docs.py
gcmd/download.py
gcmd/list.py
gcmd/sheets.py
gcmd/tasks.py
gcmd/utils.py
gcmd-0.3.0.dist-info/METADATA
gcmd-0.3.0.dist-info/WHEEL
gcmd-0.3.0.dist-info/entry_points.txt
gcmd-0.3.0.dist-info/top_level.txt
gcmd-0.3.0.dist-info/RECORD
