Metadata-Version: 2.4
Name: gcmd
Version: 0.3.0
Summary: Command-line utilities for Google services (Drive, Docs, Sheets, and more)
Author-email: Shane McDonald <me@shanemcd.com>
License: MIT
Project-URL: Homepage, https://github.com/shanemcd/gcmd
Project-URL: Repository, https://github.com/shanemcd/gcmd
Keywords: google,drive,docs,sheets,cli,utils
Classifier: Programming Language :: Python :: 3
Classifier: License :: OSI Approved :: MIT License
Classifier: Operating System :: OS Independent
Requires-Python: >=3.9
Requires-Dist: google-auth>=2.0.0
Requires-Dist: google-auth-oauthlib>=1.0.0
Requires-Dist: google-auth-httplib2>=0.1.0
Requires-Dist: google-api-python-client>=2.0.0
Requires-Dist: pypandoc>=1.11
